neco_f/__init__.py
neco_f/always_used.py
neco_f/api_.py
neco_f/auto_pip.py
neco_f/file_tools.py
neco_f/internet.py
neco_f/jiemi.py
neco_f/logger.py
neco_f/os_time.py
neco_f/pic_.py
neco_f-0.0.14.dist-info/LICENSE
neco_f-0.0.14.dist-info/METADATA
neco_f-0.0.14.dist-info/WHEEL
neco_f-0.0.14.dist-info/top_level.txt
neco_f-0.0.14.dist-info/RECORD
